README.md
setup.py
invoice_captcha/__init__.py
invoice_captcha/fake_useragent.py
invoice_captcha/utils.py
invoice_captcha.egg-info/PKG-INFO
invoice_captcha.egg-info/SOURCES.txt
invoice_captcha.egg-info/dependency_links.txt
invoice_captcha.egg-info/requires.txt
invoice_captcha.egg-info/top_level.txt