Metadata-Version: 2.1
Name: invoice-captcha
Version: 0.0.1
Summary: 国税总局发票查验验证码获取与识别.
Home-page: https://github.com/kerlomz/captcha_trainer
Author: kerlomz
Author-email: kerlomz@gmail.com
License: MIT Licence
Keywords: pip,invoice-captcha,发票查验验证码,国税验证码,税务验证码
Platform: any
Requires-Python: >=3.5
